<?xml version="1.0" encoding="UTF-8"?>
<resp>
	<code>200</code>
	<func>nshdlb</func>
	<data>
		<item type="浇水" name="王老五" time="05-21 18：20">今天浇水了今天浇水了今天浇水了今天浇水了今天浇水了今天浇水了</item>
		<item type="浇水" name="王老五" time="05-21 18：20">今天浇水了</item>
		<item type="浇水" name="王老五" time="05-21 18：20">今天浇水了</item>
		<item type="浇水" name="王老五" time="05-21 18：20">今天浇水了</item>
		<item type="浇水" name="王老五" time="05-21 18：20">今天浇水了</item>
		<item type="浇水" name="王老五" time="05-21 18：20">今天浇水了</item>
		<item type="浇水" name="王老五" time="05-21 18：20">今天浇水了</item>
		<item type="浇水" name="王老五" time="05-21 18：20">今天浇水了</item>
		<item type="浇水" name="王老五" time="05-21 18：20">今天浇水了</item>
		<item type="浇水" name="王老五" time="05-21 18：20">今天浇水了</item>
		<item type="浇水" name="王老五" time="05-21 18：20">今天浇水了</item>
		<item type="浇水" name="王老五" time="05-21 18：20">今天浇水了</item>
		<item type="浇水" name="王老五" time="05-21 18：20">今天浇水了</item>
	</data>
</resp>
